<Code>
  <Build>
    <Line from="11.8296,-4.7636" to="-10.5773,-4.7636" thickness="0.15" id="5T10w2017e22l5e20e900" interiorAlong="0" height="8" afrom="11.9046,-4.8386" ato="-10.6523,-4.8386" ifrom="11.74137,-4.675364" ito="-10.48907,-4.675364">
      <Collage struct="墙面,Collage0,0001" />
    </Line>
    <Line from="11.8296,-4.7636" to="11.8296,16.7491" thickness="0.15" id="5z10l2017Q22T5w20s901" interiorAlong="1" height="8" afrom="11.74137,-4.675364" ato="11.74137,16.66086" ifrom="11.9046,-4.8386" ito="11.9046,16.8241">
      <Collage struct="墙面,Collage0,0001" />
    </Line>
    <Line from="11.8296,16.7491" to="-10.5773,16.7491" thickness="0.15" id="5H10B2017c22E5a20x901" interiorAlong="1" height="8" afrom="11.74137,16.66086" ato="-10.48907,16.66086" ifrom="11.9046,16.8241" ito="-10.6523,16.8241">
      <Collage struct="墙面,Collage0,0001" />
    </Line>
    <Line from="-10.5773,16.7491" to="-10.5773,-4.7636" thickness="0.15" id="5v10J2017M22x5J20a901" interiorAlong="1" height="8" afrom="-10.48907,16.66086" ato="-10.48907,-4.675364" ifrom="-10.6523,16.8241" ito="-10.6523,-4.8386">
      <Collage struct="墙面,Collage0,0001" />
    </Line>
    <Line from="3.4278,-10.7638" to="-2.5722,-10.7638" thickness="0.15" id="5m10n2017J22W5U24O535" interiorAlong="0" height="8" afrom="3.5028,-10.8388" ato="-2.6472,-10.8388" ifrom="3.339565,-10.67556" ito="-2.483965,-10.67556">
      <Collage struct="墙面,Collage0,0001" />
    </Line>
    <Line from="3.4278,-10.7638" to="3.4278,-4.7636" thickness="0.15" id="5C10E2017H22G5J24I535" interiorAlong="1" height="8" afrom="3.339565,-10.67556" ato="3.339565,-4.851835" ifrom="3.5028,-10.8388" ito="3.5028,-4.6886">
      <Collage struct="墙面,Collage0,0001" />
    </Line>
    <Line from="3.4278,-4.7636" to="-2.5722,-4.7636" thickness="0.15" id="5A10R2017f22y5x24J535" interiorAlong="1" height="8" afrom="3.339565,-4.851835" ato="-2.483965,-4.851835" ifrom="3.5028,-4.6886" ito="-2.6472,-4.6886">
      <Collage struct="墙面,Collage0,0001" />
    </Line>
    <Line from="-2.5722,-4.7636" to="-2.5722,-10.7638" thickness="0.15" id="5T10R2017I22m5C24l535" interiorAlong="1" height="8" afrom="-2.483965,-4.851835" ato="-2.483965,-10.67556" ifrom="-2.6472,-4.6886" ito="-2.6472,-10.8388">
      <Collage struct="墙面,Collage0,0001" />
    </Line>
    <Surface id="5E10V2017l22C5V20r901" height="8" surfaceName="主厅" lines="5T10w2017e22l5e20e900,5z10l2017Q22T5w20s901,5H10B2017c22E5a20x901,5v10J2017M22x5J20a901">
    </Surface>
    <Surface id="5r10q2017k22A5Y24G535" height="8" surfaceName="主厅" lines="5m10n2017J22W5U24O535,5C10E2017H22G5J24I535,5A10R2017f22y5x24J535,5T10R2017I22m5C24l535">
    </Surface>
  </Build>
  <Assets>
  </Assets>
</Code>